setup.py
finisher/__init__.py
finisher/autocompleter.py
finisher/test_autocompleter.py
finisher.egg-info/PKG-INFO
finisher.egg-info/SOURCES.txt
finisher.egg-info/dependency_links.txt
finisher.egg-info/pbr.json
finisher.egg-info/requires.txt
finisher.egg-info/top_level.txt