Metadata-Version: 1.1
Name: finisher
Version: 0.1.8
Summary: Autocomplete package to train a model and return best results from input tokens
Home-page: https://github.com/slobdell/Finisher
Author: Scott Lobdell
Author-email: scott.lobdell@gmail.com
License: MIT
Keywords: python autocomplete spellcheck
Platform: UNKNOWN
Classifier: Programming Language :: Python :: 2.7
Classifier: Topic :: Other/Nonlisted Topic
